bootstrap_contrast/__init__.py
bootstrap_contrast/bootstrap_contrast.py
bootstrap_contrast/bootstrap_tools.py
bootstrap_contrast/misc_tools.py
bootstrap_contrast/plot_tools.py
bootstrap_contrast-1.0.dist-info/DESCRIPTION.rst
bootstrap_contrast-1.0.dist-info/METADATA
bootstrap_contrast-1.0.dist-info/RECORD
bootstrap_contrast-1.0.dist-info/WHEEL
bootstrap_contrast-1.0.dist-info/metadata.json
bootstrap_contrast-1.0.dist-info/top_level.txt
