Metadata-Version: 2.0
Name: bootstrap-contrast
Version: 1.0
Summary: Calculation and Visualization of Confidence Intervals and Effect Sizes for Python.
Home-page: http://github.com/josesho/bootstrap_contrast
Author: Joses Ho
Author-email: joseshowh@gmail.com
License: MIT
Platform: UNKNOWN
